wxr2md/__main__.py
wxr2md/lib.py
wxr2md-0.3.0.dist-info/LICENSE
wxr2md-0.3.0.dist-info/METADATA
wxr2md-0.3.0.dist-info/WHEEL
wxr2md-0.3.0.dist-info/RECORD
