Metadata-Version: 2.1
Name: wxr2md
Version: 0.3.0
Summary: Converter for WordPress eXport RSS (WXR) files into Markdown files
Home-page: https://github.com/nikolasdion/wxr2md
License: MIT
Keywords: wxr,wordpress,markdown
Author: Dion Susanto
Author-email: nikolasdion@gmail.com
Requires-Python: >=3.11,<4.0
Classifier: License :: OSI Approved :: MIT License
Classifier: Programming Language :: Python :: 3
Classifier: Programming Language :: Python :: 3.11
Classifier: Programming Language :: Python :: 3.12
Requires-Dist: markdownify (>=0.11.6,<0.12.0)
Requires-Dist: pyyaml (>=6.0.1,<7.0.0)
Project-URL: Repository, https://github.com/nikolasdion/wxr2md
